[
  {
    "Class": 2,
    "Section": "A",
    "First Name": "Ahad",
    "Middle Name": "Ansari",
    "Last Name": "",
    "Birth date": "30 May 2014",
    "Admission Date": "12 July 2021",
    "Admission number": 15516,
    "Address": "B863 Sangam Vihar",
    "Religion": "muslim",
    "Father name": "Javed Ahmed",
    "Mother Name": "Neelofa",
    "Category": "General",
    "Mob No": 9654273179
  },
  {
    "Class": 2,
    "Section": "A",
    "First Name": "Jatin",
    "Middle Name": "",
    "Last Name": "",
    "Birth date": "13 September 2013",
    "Admission Date": "13 July 2021",
    "Admission number": 15527,
    "Address": "E7C/673 Sangam Vihar",
    "Religion": "hindu",
    "Father name": "Sachin",
    "Mother Name": "Geeta Saraswat",
    "Category": "General",
    "Mob No": 9821857411
  },
  {
    "Class": 2,
    "Section": "A",
    "First Name": "Darsh",
    "Middle Name": "Rishi",
    "Last Name": "",
    "Birth date": "23 November 2014",
    "Admission Date": "14 September 2021",
    "Admission number": 15882,
    "Address": "B 607B Sangam Vihar",
    "Religion": "hindu",
    "Father name": "Ranvijay Singh",
    "Mother Name": "Nisha Singh",
    "Category": "General",
    "Mob No": 9810787075
  }
]